birdsMyTest/__init__.py
birdsMyTest/birds.py
birdsMyTest-0.0.4.dist-info/License.txt
birdsMyTest-0.0.4.dist-info/METADATA
birdsMyTest-0.0.4.dist-info/WHEEL
birdsMyTest-0.0.4.dist-info/top_level.txt
birdsMyTest-0.0.4.dist-info/RECORD
