Metadata-Version: 2.1
Name: birdsMyTest
Version: 0.0.4
Summary: birds atttributes and functions
Home-page: UNKNOWN
Author: megnet
Author-email: 2290906844@qq.com
License: UNKNOWN
Platform: UNKNOWN
Requires: numpy
Requires: matplotlib
License-File: License.txt
